LICENSE
MANIFEST.in
README.rst
setup.py
il2fb/ds/middleware/__init__.py
il2fb/ds/middleware/exceptions.py
il2fb/ds/middleware/text.py
il2fb/ds/middleware/console/__init__.py
il2fb/ds/middleware/console/client.py
il2fb/ds/middleware/console/constants.py
il2fb/ds/middleware/console/events.py
il2fb/ds/middleware/console/exceptions.py
il2fb/ds/middleware/console/helpers.py
il2fb/ds/middleware/console/requests.py
il2fb/ds/middleware/console/structures.py
il2fb/ds/middleware/device_link/__init__.py
il2fb/ds/middleware/device_link/client.py
il2fb/ds/middleware/device_link/constants.py
il2fb/ds/middleware/device_link/exceptions.py
il2fb/ds/middleware/device_link/filters.py
il2fb/ds/middleware/device_link/helpers.py
il2fb/ds/middleware/device_link/messages.py
il2fb/ds/middleware/device_link/parsers.py
il2fb/ds/middleware/device_link/requests.py
il2fb/ds/middleware/device_link/structures.py
il2fb_ds_middleware.egg-info/PKG-INFO
il2fb_ds_middleware.egg-info/SOURCES.txt
il2fb_ds_middleware.egg-info/dependency_links.txt
il2fb_ds_middleware.egg-info/namespace_packages.txt
il2fb_ds_middleware.egg-info/requires.txt
il2fb_ds_middleware.egg-info/top_level.txt
requirements/dist.txt