Metadata-Version: 1.1
Name: il2fb-ds-middleware
Version: 1.0.0
Summary: High-level access to IL-2 FB Dedicated Server
Home-page: https://github.com/IL2HorusTeam/il2fb-ds-middleware
Author: Alexander Oblovatniy
Author-email: oblovatniy@gmail.com
License: GPLv2
Platform: UNKNOWN
Classifier: Development Status :: 5 - Production/Stable
Classifier: Intended Audience :: Developers
Classifier: License :: Free for non-commercial use
Classifier: License :: OSI Approved :: GNU Lesser General Public License v3 (LGPLv3)
Classifier: Natural Language :: English
Classifier: Operating System :: Unix
Classifier: Operating System :: Microsoft :: Windows
Classifier: Programming Language :: Python :: 3.5
Classifier: Programming Language :: Python :: 3.6
Classifier: Topic :: Software Development :: Libraries
